caravel/__init__.py
caravel/assistant/Assistant.py
caravel/assistant/__init__.py
caravel/baml/Runner.py
caravel/baml/__init__.py
caravel/baml/baml_client/__init__.py
caravel/baml/baml_client/async_client.py
caravel/baml/baml_client/globals.py
caravel/baml/baml_client/inlinedbaml.py
caravel/baml/baml_client/partial_types.py
caravel/baml/baml_client/sync_client.py
caravel/baml/baml_client/tracing.py
caravel/baml/baml_client/type_builder.py
caravel/baml/baml_client/types.py
caravel/baml/baml_src/APIUtil_legacy.baml
caravel/baml/baml_src/ContextManager.baml
caravel/baml/baml_src/DynamicAPI.baml
caravel/baml/baml_src/Intent_legacy.baml
caravel/baml/baml_src/MakePath_legacy.baml
caravel/baml/baml_src/ParsingTransform_unused.baml
caravel/baml/baml_src/Retry.baml
caravel/baml/baml_src/clients.baml
caravel/baml/baml_src/generators.baml
caravel/http/Client.py
caravel/parsing/Parser.py
caravel/parsing/__init__.py
caravel/utils/__init__.py
caravel/utils/utils.py
caravel_ai-0.0.3.dist-info/LICENSE
caravel_ai-0.0.3.dist-info/METADATA
caravel_ai-0.0.3.dist-info/WHEEL
caravel_ai-0.0.3.dist-info/RECORD
