Metadata-Version: 2.3
Name: caravel-ai
Version: 0.0.3
Summary: 
Author: cannonhutcheson
Author-email: cannonhutcheson@proton.me
Requires-Python: >=3.11
Classifier: Programming Language :: Python :: 3
Classifier: Programming Language :: Python :: 3.11
Classifier: Programming Language :: Python :: 3.12
Classifier: Programming Language :: Python :: 3.13
Requires-Dist: baml-py (==0.78.0)
Requires-Dist: dotenv (>=0.9.9,<0.10.0)
Requires-Dist: httpx (>=0.28.1,<0.29.0)
Requires-Dist: pydantic (>=2.10.6,<3.0.0)
Requires-Dist: pyyaml (>=6.0.2,<7.0.0)
Requires-Dist: ruamel-yaml (>=0.18.10,<0.19.0)
